Source/clock_divider.v
module clock_divider(
 
    //////////// CLOCK //////////
    input                       clk,
    input                       reset_n,
    output                      slower_clk      //calculate correct size!                
);
 
parameter clk_div = 0;
 
reg [23:0] div_cntr;
reg slw_clk;
 
always @(posedge clk, negedge reset_n)
    begin
        if(reset_n == 0)
            begin
                div_cntr <= 0;
            end
        else if(div_cntr == clk_div - 1)
            begin
                div_cntr <= 0;
                slw_clk <= ~slw_clk;
            end
        else
            begin
                div_cntr <= div_cntr + 1;
            end
    end

assign slower_clk = slw_clk;

endmodule

Source/TB_clock_divider.v
`timescale 1 ns / 100 ps

module TB_clock_divider();

    reg clk;
    reg Rn;
    wire SCLK;

    clock_divider #(5) CD0 (
        .clk(clk),
        .reset_n(Rn),
        .slower_clk(SCLK)
    );

    initial
        begin
            clk = 1'b0;
            Rn = 1'b0;
        #10 Rn = 1'b1;
        end

    always
        #5 clk = ~clk;

    initial
        begin
            $dumpfile("output.vcd");
            $dumpvars;
            $display("Starting simulation");
        end   

    initial
        begin
            $monitor("%d,\t%b,\t%b", $time, clk, Rn, SCLK);        
        end

        initial
            begin
                $display("Simulation ended.");
                #1000 $finish;
            end
        
endmodule

Source/SevenSeg.v
module SevenSeg(
 
    //////////// SEG7 //////////
    output           [7:0]      HEX,
 
    //////////// KEY //////////
    input            [7:0]     NUM
    
);
 
    reg [7:0] value;
 
//takes decimal number and converts to binary for HEX display based on logic 0 = on, logic 1 = off for each segment
//if NUM = 'd88 is blank(pos)
//if NUM = 'd99 is minus sign
    always @(NUM)
        begin
            case(NUM)
                8'd0: value = 8'b11000000;
                8'd1: value = 8'b11111001;
                8'd2: value = 8'b10100100;
                8'd3: value = 8'b10110000;
                8'd4: value = 8'b10011001;
                8'd5: value = 8'b10010010;
                8'd6: value = 8'b10000010;
                8'd7: value = 8'b11111000;
                8'd8: value = 8'b10000000;
                8'd9: value = 8'b10011000;
                // 8'd10: value = 8'b10001000; 
                // 8'd11: value = 8'b10000011;
                // 8'd12: value = 8'b11000110;
                // 8'd13: value = 8'b10100001;
                // 8'd14: value = 8'b10000110;
                // 8'd15: value = 8'b10001110;
 
                8'd88: value = 8'b11111111;
                // 8'd99: value = 8'b10111111;
            endcase
        end
 
 
    //the HEX display passed is given whatever value determined above
    assign HEX[7:0] = value;
 
 
endmodule

Source/day_display.v
module day_display(
    //////////// Counters //////////
    input            [7:0]      day_full,
 
    //////////// SEG7 //////////
    output           [7:0]      HEX0,
    output           [7:0]      HEX1
);
 
reg [7:0] counter_tens_p;
reg [7:0] counter_ones_p;

always @(day_full)
    begin
        if(day_full <= 8'd9)
            begin
                counter_tens_p <= 8'd88;
                counter_ones_p <= day_full;
            end
        else if(day_full <= 8'd19)
            begin
                counter_tens_p <= 8'd1;
                counter_ones_p <= day_full - 10;
            end
        else if(day_full <= 8'd29)
            begin
                counter_tens_p <= 8'd2;
                counter_ones_p <= day_full - 20;
            end
        else if(day_full <= 8'd39)
            begin
                counter_tens_p <= 8'd3;
                counter_ones_p <= day_full - 30;
            end
        else
            begin
                counter_tens_p <= 8'd88;
                counter_tens_p <= 8'd88;
            end
    end
 
SevenSeg SS1(.HEX(HEX1), .NUM(counter_tens_p)); 
SevenSeg SS0(.HEX(HEX0), .NUM(counter_ones_p));

endmodule

Source/month_day.v
module month_day(
    //////////// Counters //////////
    input            [7:0]      total_count,

    //////////// LEAP YEAR //////////
    input           [7:0]       feb_day,
 
    //////////// SEG7 //////////
    output           [7:0]      HEX0,
    output           [7:0]      HEX1,
    output           [7:0]      HEX2,
    output           [7:0]      HEX3
);
 
reg [7:0] disp_month;
reg [7:0] counter_tens_p;
reg [7:0] counter_ones_p;
reg [7:0] day_full;
 
always @(total_count)
    begin
        if(total_count <= 8'd31)
            begin
                disp_month <= 8'd1;
                day_full <= total_count;
            end
        else if(total_count <= (8'd31 + feb_day))
            begin
                disp_month <= 8'd2;
                day_full <= total_count - 8'd31;
            end
        else if(total_count <= (8'd31 + feb_day + 8'd31))
            begin
                disp_month <= 8'd3;
                day_full <= total_count - (8'd31 + feb_day);
            end
        else
            begin
                disp_month <= 8'd4;
                day_full <= total_count - (8'd31 + feb_day + 8'd31);
            end
    end

SevenSeg SS3(.HEX(HEX3), .NUM(8'd88));
SevenSeg SS2(.HEX(HEX2), .NUM(disp_month));

day_display DD(.day_full(day_full), .HEX0(HEX0), .HEX1(HEX1));


endmodule

Source/Counters.v
module Counters(
    input                       clk,
    input                       reset_n,

    //////////// LEAP YEAR //////////
    input           [7:0]       feb_day,
 
    //////////// SEG7 //////////
    output           [7:0]      HEX0,
    output           [7:0]      HEX1,
    output           [7:0]      HEX2,
    output           [7:0]      HEX3,
    output           [7:0]      HEX4,
    output           [7:0]      HEX5
);
 
reg [7:0] counter_tens_p;
reg [7:0] counter_ones_p;
reg [7:0] total_count;
 
always @(posedge clk, negedge reset_n)
    begin
        if(reset_n == 0)
            begin
                counter_tens_p <= 8'd88;
                counter_ones_p <= 8'd1;
                total_count <= 8'd1;
            end
        else
            begin
                if(counter_ones_p != 8'd9)
                    begin
                        counter_ones_p <= counter_ones_p + 1;
                        total_count <= total_count + 1;
                    end
                else if(counter_ones_p == 8'd9)
                    begin
                        if(counter_tens_p == 8'd88)
                            begin
                                counter_tens_p <= 8'd1;
                                counter_ones_p <= 8'd0;
                                total_count <= total_count + 1;
                            end
                        else if(counter_tens_p == 8'd9)
                            begin
                                counter_tens_p <= 8'd88;
                                counter_ones_p <= 8'd1;
                                total_count <= 8'd1;
                            end
                        else
                            begin
                                counter_tens_p <= counter_tens_p + 1;
                                counter_ones_p <= 8'd0;
                                total_count <= total_count + 1;
                            end
                    end
            end
    end
 
    SevenSeg W0(.HEX(HEX5), .NUM(counter_tens_p)); 
    SevenSeg W1(.HEX(HEX4), .NUM(counter_ones_p));

    month_day MD0(.total_count(total_count), .feb_day(feb_day), .HEX0(HEX0), .HEX1(HEX1), .HEX2(HEX2), .HEX3(HEX3));

endmodule

Source/clock_choice.v
module clock_choice(
    input                       select,

    input                       latch,
    output                      s_clk,

	input                       s1,
    input            [0:0]      s2
);

    reg SCLK;
    
    assign s_clk = SCLK;

    always @(select)
        begin
            case(select)
                0: SCLK = s1;
                1: SCLK = s2;
            endcase 
        end

    assign s_clk = SCLK;

endmodule

Source/Lab2.v
//=======================================================
//  This code is generated by Terasic System Builder
//=======================================================
 
module Lab2(
 
    //////////// CLOCK //////////
    input                       ADC_CLK_10,
    input                       MAX10_CLK1_50,
    input                       MAX10_CLK2_50,
 
    //////////// SEG7 //////////
    output           [7:0]      HEX0,
    output           [7:0]      HEX1,
    output           [7:0]      HEX2,
    output           [7:0]      HEX3,
    output           [7:0]      HEX4,
    output           [7:0]      HEX5,
 
    //////////// KEY //////////
    input            [1:0]      KEY,
 
    //////////// LED //////////
    output           [9:0]      LEDR,
 
    //////////// SW //////////
    input            [9:0]      SW
);
 

reg [7:0] feb_day;
always @(SW[9])
    begin
        if(SW[9] == 1)
            feb_day <= 8'd29;
        else
            feb_day <= 8'd28;
    end


wire s_clk;
assign LEDR[1] = s_clk;
wire s_clk_1;
wire s_clk_2;

reg div_val = 1'b1;
wire val;

always @(negedge KEY[1])
    begin
        div_val <= ~div_val;
    end

assign val = div_val;


reg latch_out = 1'b0;
wire latch; 

always @(negedge KEY[0])
	begin
    	latch_out <= ~latch_out;
	end
 
assign latch = latch_out;
assign LEDR[0] = latch;


clock_divider #(1_000_000) CD0(.clk(ADC_CLK_10), .reset_n(latch), .slower_clk(s_clk_1));
clock_divider #(5_000_000) CD1(.clk(ADC_CLK_10), .reset_n(latch), .slower_clk(s_clk_2));

clock_choice CC0(.select(val), .latch(latch), .s_clk(s_clk), .s1(s_clk_1), .s2(s_clk_2));
 
Counters C1(.clk(s_clk), .reset_n(latch), .feb_day(feb_day), .HEX0(HEX0), .HEX1(HEX1), .HEX2(HEX2), .HEX3(HEX3), .HEX4(HEX4), .HEX5(HEX5));

 
endmodule

Source/output.vcd
$date
	Wed Nov 06 22:07:57 2019
$end
$version
	Icarus Verilog
$end
$timescale
	100ps
$end
$scope module Lab2 $end
$var wire 1 ! ADC_CLK_10 $end
$var wire 2 " KEY [1:0] $end
$var wire 1 # MAX10_CLK1_50 $end
$var wire 1 $ MAX10_CLK2_50 $end
$var wire 10 % SW [9:0] $end
$var wire 1 & s_clk $end
$var wire 1 ' val $end
$var wire 1 ( s_clk_2 $end
$var wire 1 ) s_clk_1 $end
$var wire 1 * latch $end
$var wire 10 + LEDR [9:0] $end
$var wire 8 , HEX5 [7:0] $end
$var wire 8 - HEX4 [7:0] $end
$var wire 8 . HEX3 [7:0] $end
$var wire 8 / HEX2 [7:0] $end
$var wire 8 0 HEX1 [7:0] $end
$var wire 8 1 HEX0 [7:0] $end
$var reg 1 2 div_val $end
$var reg 8 3 feb_day [7:0] $end
$var reg 1 * latch_out $end
$scope module C1 $end
$var wire 1 & clk $end
$var wire 8 4 feb_day [7:0] $end
$var wire 1 * reset_n $end
$var wire 8 5 HEX5 [7:0] $end
$var wire 8 6 HEX4 [7:0] $end
$var wire 8 7 HEX3 [7:0] $end
$var wire 8 8 HEX2 [7:0] $end
$var wire 8 9 HEX1 [7:0] $end
$var wire 8 : HEX0 [7:0] $end
$var reg 8 ; counter_ones_p [7:0] $end
$var reg 8 < counter_tens_p [7:0] $end
$var reg 8 = total_count [7:0] $end
$scope module MD0 $end
$var wire 8 > feb_day [7:0] $end
$var wire 8 ? total_count [7:0] $end
$var wire 8 @ HEX3 [7:0] $end
$var wire 8 A HEX2 [7:0] $end
$var wire 8 B HEX1 [7:0] $end
$var wire 8 C HEX0 [7:0] $end
$var reg 8 D day_full [7:0] $end
$var reg 8 E disp_month [7:0] $end
$scope module DD $end
$var wire 8 F day_full [7:0] $end
$var wire 8 G HEX1 [7:0] $end
$var wire 8 H HEX0 [7:0] $end
$var reg 8 I counter_ones_p [7:0] $end
$var reg 8 J counter_tens_p [7:0] $end
$scope module SS0 $end
$var wire 8 K HEX [7:0] $end
$var wire 8 L NUM [7:0] $end
$var reg 8 M value [7:0] $end
$upscope $end
$scope module SS1 $end
$var wire 8 N HEX [7:0] $end
$var wire 8 O NUM [7:0] $end
$var reg 8 P value [7:0] $end
$upscope $end
$upscope $end
$scope module SS2 $end
$var wire 8 Q HEX [7:0] $end
$var wire 8 R NUM [7:0] $end
$var reg 8 S value [7:0] $end
$upscope $end
$scope module SS3 $end
$var wire 8 T HEX [7:0] $end
$var wire 8 U NUM [7:0] $end
$var reg 8 V value [7:0] $end
$upscope $end
$upscope $end
$scope module W0 $end
$var wire 8 W HEX [7:0] $end
$var wire 8 X NUM [7:0] $end
$var reg 8 Y value [7:0] $end
$upscope $end
$scope module W1 $end
$var wire 8 Z HEX [7:0] $end
$var wire 8 [ NUM [7:0] $end
$var reg 8 \ value [7:0] $end
$upscope $end
$upscope $end
$scope module CC0 $end
$var wire 1 * latch $end
$var wire 1 & s_clk $end
$var wire 1 ' select $end
$var wire 1 ( s2 $end
$var wire 1 ) s1 $end
$var reg 1 ] SCLK $end
$upscope $end
$scope module CD0 $end
$var wire 1 ! clk $end
$var wire 1 * reset_n $end
$var wire 1 ) slower_clk $end
$var reg 24 ^ div_cntr [23:0] $end
$var reg 1 _ slw_clk $end
$upscope $end
$scope module CD1 $end
$var wire 1 ! clk $end
$var wire 1 * reset_n $end
$var wire 1 ( slower_clk $end
$var reg 24 ` div_cntr [23:0] $end
$var reg 1 a slw_clk $end
$upscope $end
$upscope $end
$scope module TB_clock_divider $end
$var wire 1 b SCLK $end
$var reg 1 c Rn $end
$var reg 1 d clk $end
$scope module CD0 $end
$var wire 1 d clk $end
$var wire 1 c reset_n $end
$var wire 1 b slower_clk $end
$var reg 24 e div_cntr [23:0] $end
$var reg 1 f slw_clk $end
$upscope $end
$upscope $end
$enddefinitions $end
#0
$dumpvars
xf
b0 e
0d
0c
xb
xa
b0 `
x_
b0 ^
x]
b11111001 \
b1 [
b11111001 Z
b11111111 Y
b1011000 X
b11111111 W
b11111111 V
b1011000 U
b11111111 T
b11111001 S
b1 R
b11111001 Q
b11111111 P
b1011000 O
b11111111 N
b11111001 M
b1 L
b11111001 K
b1011000 J
b1 I
b11111001 H
b11111111 G
b1 F
b1 E
b1 D
b11111001 C
b11111111 B
b11111001 A
b11111111 @
b1 ?
b11100 >
b1 =
b1011000 <
b1 ;
b11111001 :
b11111111 9
b11111001 8
b11111111 7
b11111001 6
b11111111 5
b11100 4
b11100 3
12
b11111001 1
b11111111 0
b11111001 /
b11111111 .
b11111001 -
b11111111 ,
bzx0 +
0*
x)
x(
1'
x&
bz %
z$
z#
bz "
z!
$end
#50
1d
#100
0d
1c
#150
b1 e
1d
#200
0d
#250
b10 e
1d
#300
0d
#350
b11 e
1d
#400
0d
#450
b100 e
1d
#500
0d
#550
b0 e
1d
#600
0d
#650
b1 e
1d
#700
0d
#750
b10 e
1d
#800
0d
#850
b11 e
1d
#900
0d
#950
b100 e
1d
#1000
0d
#1050
b0 e
1d
#1100
0d
#1150
b1 e
1d
#1200
0d
#1250
b10 e
1d
#1300
0d
#1350
b11 e
1d
#1400
0d
#1450
b100 e
1d
#1500
0d
#1550
b0 e
1d
#1600
0d
#1650
b1 e
1d
#1700
0d
#1750
b10 e
1d
#1800
0d
#1850
b11 e
1d
#1900
0d
#1950
b100 e
1d
#2000
0d
#2050
b0 e
1d
#2100
0d
#2150
b1 e
1d
#2200
0d
#2250
b10 e
1d
#2300
0d
#2350
b11 e
1d
#2400
0d
#2450
b100 e
1d
#2500
0d
#2550
b0 e
1d
#2600
0d
#2650
b1 e
1d
#2700
0d
#2750
b10 e
1d
#2800
0d
#2850
b11 e
1d
#2900
0d
#2950
b100 e
1d
#3000
0d
#3050
b0 e
1d
#3100
0d
#3150
b1 e
1d
#3200
0d
#3250
b10 e
1d
#3300
0d
#3350
b11 e
1d
#3400
0d
#3450
b100 e
1d
#3500
0d
#3550
b0 e
1d
#3600
0d
#3650
b1 e
1d
#3700
0d
#3750
b10 e
1d
#3800
0d
#3850
b11 e
1d
#3900
0d
#3950
b100 e
1d
#4000
0d
#4050
b0 e
1d
#4100
0d
#4150
b1 e
1d
#4200
0d
#4250
b10 e
1d
#4300
0d
#4350
b11 e
1d
#4400
0d
#4450
b100 e
1d
#4500
0d
#4550
b0 e
1d
#4600
0d
#4650
b1 e
1d
#4700
0d
#4750
b10 e
1d
#4800
0d
#4850
b11 e
1d
#4900
0d
#4950
b100 e
1d
#5000
0d
#5050
b0 e
1d
#5100
0d
#5150
b1 e
1d
#5200
0d
#5250
b10 e
1d
#5300
0d
#5350
b11 e
1d
#5400
0d
#5450
b100 e
1d
#5500
0d
#5550
b0 e
1d
#5600
0d
#5650
b1 e
1d
#5700
0d
#5750
b10 e
1d
#5800
0d
#5850
b11 e
1d
#5900
0d
#5950
b100 e
1d
#6000
0d
#6050
b0 e
1d
#6100
0d
#6150
b1 e
1d
#6200
0d
#6250
b10 e
1d
#6300
0d
#6350
b11 e
1d
#6400
0d
#6450
b100 e
1d
#6500
0d
#6550
b0 e
1d
#6600
0d
#6650
b1 e
1d
#6700
0d
#6750
b10 e
1d
#6800
0d
#6850
b11 e
1d
#6900
0d
#6950
b100 e
1d
#7000
0d
#7050
b0 e
1d
#7100
0d
#7150
b1 e
1d
#7200
0d
#7250
b10 e
1d
#7300
0d
#7350
b11 e
1d
#7400
0d
#7450
b100 e
1d
#7500
0d
#7550
b0 e
1d
#7600
0d
#7650
b1 e
1d
#7700
0d
#7750
b10 e
1d
#7800
0d
#7850
b11 e
1d
#7900
0d
#7950
b100 e
1d
#8000
0d
#8050
b0 e
1d
#8100
0d
#8150
b1 e
1d
#8200
0d
#8250
b10 e
1d
#8300
0d
#8350
b11 e
1d
#8400
0d
#8450
b100 e
1d
#8500
0d
#8550
b0 e
1d
#8600
0d
#8650
b1 e
1d
#8700
0d
#8750
b10 e
1d
#8800
0d
#8850
b11 e
1d
#8900
0d
#8950
b100 e
1d
#9000
0d
#9050
b0 e
1d
#9100
0d
#9150
b1 e
1d
#9200
0d
#9250
b10 e
1d
#9300
0d
#9350
b11 e
1d
#9400
0d
#9450
b100 e
1d
#9500
0d
#9550
b0 e
1d
#9600
0d
#9650
b1 e
1d
#9700
0d
#9750
b10 e
1d
#9800
0d
#9850
b11 e
1d
#9900
0d
#9950
b100 e
1d
